<?xml version="1.0" encoding="UTF-8"?>
<playlist version="1" xmlns="http://xspf.org/ns/0/">
<trackList>
<track>
<album>All That You Can't Leave Behind</album>
	<creator>U2</creator>
	<title>Walk On</title>
</track>
<track>
<album>In The Beginning There Was Rhythm</album>
	<creator>23 Skidoo</creator>
	<title>Coup</title>
</track>
<track>
<album>Early</album>
	<creator>A Certain Ratio</creator>
	<title>Waterline</title>
</track>
<track>
<album>Tourist</album>
	<creator>St Germain</creator>
	<title>Sure Thing</title>
</track>
<track>
<album>Born On The 24th July</album>
	<creator>Charles Webster</creator>
	<title>The Gift of Freedom</title>
</track>
<track>
<album>The Big Romance</album>
	<creator>David Kitt</creator>
	<title>You Know What I Want</title>
</track>
<track>
<album>Apollo</album>
	<creator>Brian Eno</creator>
	<title>Deep Blue Day</title>
</track>
<track>
<album>On Their Corner</album>
	<creator>The Dells</creator>
	<title>I Can Sing A Rainbow</title>
</track>
<track>
<album>The Best of Isaac Hayes</album>
	<creator>Isaac Hayes</creator>
	<title>Walk On By</title>
</track>
<track>
<album>Blood Money</album>
	<creator>Tom Waits</creator>
	<title>Misery Is The River Of The World</title>
</track>
<track>
<album>Blues &amp; Roots</album>
	<creator>Charles Mingus</creator>
	<title>Moanin</title>
</track>
<track>
<album>Bramble Rose</album>
	<creator>Tift Merritt</creator>
	<title>Are You Still In Love With Me</title>
</track>
<track>
<album>My Favourites of Hank Williams/Trouble In Mind</album>
	<creator>George Jones</creator>
	<title>Brown To Blue</title>
</track>
<track>
<album>Turn The Dark Off</album>
	<creator>Howie B</creator>
	<title>Take Your Partner By The Hand</title>
</track>
<track>
<album>HATS</album>
	<creator>The Blue Nile</creator>
	<title>Let</title>
</track>
<track>
<album>Agaetis Byrjun</album>
	<creator>Signur Ros</creator>
	<title>Staalfur</title>
</track>
<track>
<album>Kind Of Blue</album>
	<creator>Miles Davis</creator>
	<title>Blue In Green</title>
</track>
</trackList>
</playlist>
