<?xml version="1.0" encoding="UTF-8"?>
<playlist version="1" xmlns="http://xspf.org/ns/0/">
<trackList>
<track>
<album>PROMO CD</album>
	<creator>REM</creator>
	<title>LOSING MY RELIGION</title>
</track>
<track>
<album>TRACKS FROM THE VAULTS</album>
	<creator>HORSLIPS</creator>
	<title>GREEN GRAVEL</title>
</track>
<track>
<album>HERESIE</album>
	<creator>THE VIRGIN PRUNES</creator>
	<title>DOWN THE MEMORY LANE</title>
</track>
<track>
<album>LOCAL GROUND</album>
	<creator>ALTAN</creator>
	<title>TOMMY PEOPLES ETC</title>
</track>
<track>
<album>CHAVEZ RAVINE</album>
	<creator>RY COODER</creator>
	<title>3 COOL CATS</title>
</track>
<track>
<album>THE MURKY WORLD OF BARRY ADAMSON</album>
	<creator>BARRY ADAMSON</creator>
	<title>007 FANTASY BOND THEME</title>
</track>
<track>
<album>PSYCHADELIC SOUL</album>
	<creator>THE TEMPTATIONS</creator>
	<title>BALL OF CONFUSION</title>
</track>
<track>
<album>BLACKNUSS</album>
	<creator>RAHSHAAN ROLAND KIRK</creator>
	<title>MY GIRL</title>
</track>
<track>
<album>THE KINGS OF FUNK</album>
	<creator>HARLEM UNDERGROUND BAND</creator>
	<title>AINT NO SUNSHINE</title>
</track>
<track>
<album>LEAN ON ME</album>
	<creator>BILL WITHERS</creator>
	<title>KISSIN MY LOVE</title>
</track>
<track>
<album>ANTHOLOGY</album>
	<creator>ESTHER PHILLIPS</creator>
	<title>USE ME</title>
</track>
<track>
<album>ECSTASY</album>
	<creator>LOU REED</creator>
	<title>DOIN A MODERN DANCE</title>
</track>
<track>
<album>THE DEFINITIVE MONKEES</album>
	<creator>THE MONKEES</creator>
	<title>LAST TRAIN TO CLARKSVILLE</title>
</track>
<track>
<album>GRAVICHORDS WHIRLIES &amp; PYROPHONES</album>
	<creator>CLARA ROCKMORE</creator>
	<title>THE SWAN</title>
</track>
<track>
<album>MUSICAL GENIUS AND SEX SYMBOL</album>
	<creator>EARL OKIN</creator>
	<title>YELLOW</title>
</track>
<track>
<album>THE SPECTACULAR SADNESS OF REX HOBART</album>
	<creator>REX HOBART AND THE MISERY BOYS</creator>
	<title>NOT DRUNK ENOUGH TO SAY</title>
</track>
<track>
<album>DEEP PURPLE 30  THE BEST OF</album>
	<creator>DEEP PURPLE</creator>
	<title>BURN</title>
</track>
</trackList>
</playlist>
