<?xml version="1.0" encoding="UTF-8"?>
<playlist version="1" xmlns="http://xspf.org/ns/0/">
<trackList>
<track>
<album>The Essential Porter Wagoner</album>
	<creator>Porter Wagoner</creator>
	<title>What Would You Do</title>
</track>
<track>
<album>Hello Starling</album>
	<creator>Josh Ritter</creator>
	<title>Kathleen</title>
</track>
<track>
<album>Consent</album>
	<creator>The Devlins</creator>
	<title>There Is A Light</title>
</track>
<track>
<album>Crawfish Fiesta</album>
	<creator>Professor Longhair</creator>
	<title>It</title>
</track>
<track>
<album>Released, A Memorial Album</album>
	<creator>Johnny Adams</creator>
	<title>Release Me</title>
</track>
<track>
<album>Released, A Memorial Album</album>
	<creator>Johnny Adams</creator>
	<title>Reconsider Me</title>
</track>
<track>
<album>Randy Newman Songbook, Vol 1</album>
	<creator>Randy Newman</creator>
	<title>Louisiana 1927</title>
</track>
<track>
<album>What's Wrong With This Picture?</album>
	<creator>Van Morrison</creator>
	<title>What</title>
</track>
<track>
<album>Rum Sodomy &amp; The Lash</album>
	<creator>The Pogues</creator>
	<title>A Pair Of Brown Eyes</title>
</track>
<track>
<album>Ralph Stanley</album>
	<creator>Ralph Stanley</creator>
	<title>Girl From Greenbriar Shore</title>
</track>
<track>
<album>The Civil War</album>
	<creator>Matmos</creator>
	<title>For The Trees</title>
</track>
</trackList>
</playlist>
